aiwriter/__init__.py
aiwriter/cli.py
aiwriter/env.py
aiwriter/agents/__init__.py
aiwriter/agents/context_builder.py
aiwriter/agents/editor.py
aiwriter/agents/ranker.py
aiwriter/agents/thinker.py
aiwriter/agents/writer.py
aiwriter-0.1.3.dist-info/licenses/LICENSE
aiwriter-0.1.3.dist-info/METADATA
aiwriter-0.1.3.dist-info/WHEEL
aiwriter-0.1.3.dist-info/entry_points.txt
aiwriter-0.1.3.dist-info/top_level.txt
aiwriter-0.1.3.dist-info/RECORD
