Metadata-Version: 2.4
Name: aiwriter
Version: 0.1.3
Summary: AIWriter is an AI Agent for writers.
Author-email: Marcos Cannabrava <mpcannabrava@gmail.com>
Requires-Python: >=3.12
License-File: LICENSE
Requires-Dist: anthropic>=0.51.0
Requires-Dist: bs4>=0.0.2
Requires-Dist: click>=8.1.8
Requires-Dist: instructor>=1.8.2
Requires-Dist: requests>=2.32.3
Dynamic: license-file
